hiraconf/__init__.py
hiraconf/parser.py
hiraconf/provider.py
hiraconf/py.typed
hiraconf-0.1.1.dist-info/METADATA
hiraconf-0.1.1.dist-info/WHEEL
hiraconf-0.1.1.dist-info/licenses/LICENSE
hiraconf-0.1.1.dist-info/RECORD
