Metadata-Version: 2.3
Name: hiraconf
Version: 0.1.1
Summary: Hierarchical config parser
Project-URL: Repository, https://github.com/crxwns/HiraConf
Author: crxwns
License: MIT License
License-File: LICENSE
Requires-Python: >=3.11
Requires-Dist: pydantic>=2.8.2
Requires-Dist: pyyaml>=6.0.2
